[
    {
        "name": "news",
        "source": "distrowatch",
        "url": "https://distrowatch.com/news/dw.xml"
    },
    {
        "name": "torrent",
        "source": "distrowatch",
        "url": "https://distrowatch.com/news/torrents.xml" 
    },
    {
        "name": "security",
        "source": "linuxsecurity",
        "url": "https://linuxsecurity.com/linuxsecurity_advisories.xml" 
    },
    {
        "name": "release",
        "source": "distrowatch",
        "url": "https://distrowatch.com/news/dwd.xml" 
    }
]